{"audioUrl": "", "duration": 3609.275, "paragraphs": [{"id": "p1", "sentences": [{"id": "p1s1", "text": "Mi recorrido por el mercado local siempre comienza con el dulce aroma de las fresas frescas.", "boundaries": [{"text": "Mi ", "start": 0.0, "end": 0.151}, {"text": "recorrido ", "start": 0.209, "end": 0.72}, {"text": "por ", "start": 0.778, "end": 0.906}, {"text": "el ", "start": 0.952, "end": 0.998}, {"text": "mercado ", "start": 1.045, "end": 1.416}, {"text": "local ", "start": 1.463, "end": 1.834}, {"text": "siempre ", "start": 1.916, "end": 2.229}, {"text": "comienza ", "start": 2.264, "end": 2.728}, {"text": "con ", "start": 2.775, "end": 2.914}, {"text": "el ", "start": 2.972, "end": 3.042}, {"text": "dulce ", "start": 3.1, "end": 3.471}, {"text": "aroma ", "start": 3.529, "end": 3.889}, {"text": "de ", "start": 3.947, "end": 4.005}, {"text": "las ", "start": 4.052, "end": 4.18}, {"text": "fresas ", "start": 4.238, "end": 4.632}, {"text": "frescas.", "start": 4.69, "end": 5.352}]}, {"id": "p1s2", "text": "Los sábados por la mañana temprano, los puestos están llenos de colores vibrantes y caras amigables.", "boundaries": [{"text": "Los ", "start": 5.944, "end": 6.118}, {"text": "sábados ", "start": 6.142, "end": 6.513}, {"text": "por ", "start": 6.56, "end": 6.676}, {"text": "la ", "start": 6.722, "end": 6.78}, {"text": "mañana ", "start": 6.827, "end": 7.152}, {"text": "temprano, ", "start": 7.198, "end": 7.918}, {"text": "los ", "start": 8.127, "end": 8.278}, {"text": "puestos ", "start": 8.336, "end": 8.684}, {"text": "están ", "start": 8.742, "end": 9.021}, {"text": "llenos ", "start": 9.056, "end": 9.404}, {"text": "de ", "start": 9.439, "end": 9.497}, {"text": "colores ", "start": 9.543, "end": 9.938}, {"text": "vibrantes ", "start": 9.985, "end": 10.612}, {"text": "y ", "start": 10.67, "end": 10.704}, {"text": "caras ", "start": 10.751, "end": 11.064}, {"text": "amigables.", "start": 11.134, "end": 11.958}]}, {"id": "p1s3", "text": "Me encanta curiosear por la variada selección de verduras ecológicas y quesos artesanales.", "boundaries": [{"text": "Me ", "start": 12.55, "end": 12.666}, {"text": "encanta ", "start": 12.69, "end": 13.096}, {"text": "curiosear ", "start": 13.142, "end": 13.781}, {"text": "por ", "start": 13.851, "end": 13.978}, {"text": "la ", "start": 14.036, "end": 14.118}, {"text": "variada ", "start": 14.153, "end": 14.536}, {"text": "selección ", "start": 14.594, "end": 15.186}, {"text": "de ", "start": 15.233, "end": 15.302}, {"text": "verduras ", "start": 15.337, "end": 15.906}, {"text": "ecológicas ", "start": 15.964, "end": 16.73}, {"text": "y ", "start": 16.846, "end": 16.928}, {"text": "quesos ", "start": 16.997, "end": 17.357}, {"text": "artesanales.", "start": 17.415, "end": 18.356}]}]}, {"id": "p2", "sentences": [{"id": "p2s1", "text": "La vendedora de miel local siempre cuenta historias fascinantes sobre sus colmenas en el campo.", "boundaries": [{"text": "La ", "start": 19.223, "end": 19.386}, {"text": "vendedora ", "start": 19.432, "end": 19.954}, {"text": "de ", "start": 20.001, "end": 20.071}, {"text": "miel ", "start": 20.129, "end": 20.303}, {"text": "local ", "start": 20.338, "end": 20.744}, {"text": "siempre ", "start": 20.837, "end": 21.243}, {"text": "cuenta ", "start": 21.278, "end": 21.591}, {"text": "historias ", "start": 21.638, "end": 22.16}, {"text": "fascinantes ", "start": 22.218, "end": 23.101}, {"text": "sobre ", "start": 23.182, "end": 23.472}, {"text": "sus ", "start": 23.507, "end": 23.658}, {"text": "colmenas ", "start": 23.704, "end": 24.215}, {"text": "en ", "start": 24.273, "end": 24.331}, {"text": "el ", "start": 24.378, "end": 24.447}, {"text": "campo.", "start": 24.506, "end": 25.121}]}, {"id": "p2s2", "text": "Casi siempre me llevo un tarro de miel de mil flores y una hogaza de pan de masa madre.", "boundaries": [{"text": "Casi ", "start": 25.713, "end": 26.015}, {"text": "siempre ", "start": 26.061, "end": 26.444}, {"text": "me ", "start": 26.491, "end": 26.584}, {"text": "llevo ", "start": 26.607, "end": 26.874}, {"text": "un ", "start": 26.99, "end": 27.129}, {"text": "tarro ", "start": 27.211, "end": 27.524}, {"text": "de ", "start": 27.571, "end": 27.64}, {"text": "miel ", "start": 27.698, "end": 27.977}, {"text": "de ", "start": 28.047, "end": 28.128}, {"text": "mil ", "start": 28.186, "end": 28.383}, {"text": "flores ", "start": 28.453, "end": 28.952}, {"text": "y ", "start": 29.068, "end": 29.126}, {"text": "una ", "start": 29.161, "end": 29.324}, {"text": "hogaza ", "start": 29.359, "end": 29.823}, {"text": "de ", "start": 29.893, "end": 29.962}, {"text": "pan ", "start": 30.02, "end": 30.264}, {"text": "de ", "start": 30.334, "end": 30.415}, {"text": "masa ", "start": 30.473, "end": 30.775}, {"text": "madre.", "start": 30.833, "end": 31.437}]}, {"id": "p2s3", "text": "Es maravilloso apoyar a los productores dedicados de nuestra comunidad.", "boundaries": [{"text": "Es ", "start": 32.029, "end": 32.203}, {"text": "maravilloso ", "start": 32.249, "end": 32.981}, {"text": "apoyar ", "start": 33.039, "end": 33.422}, {"text": "a ", "start": 33.48, "end": 33.503}, {"text": "los ", "start": 33.538, "end": 33.677}, {"text": "productores ", "start": 33.724, "end": 34.328}, {"text": "dedicados ", "start": 34.374, "end": 34.989}, {"text": "de ", "start": 35.047, "end": 35.129}, {"text": "nuestra ", "start": 35.187, "end": 35.547}, {"text": "comunidad.", "start": 35.593, "end": 36.336}]}]}, {"id": "p3", "sentences": [{"id": "p3s1", "text": "Mientras vuelvo para casa, mi cesta pesa por la mejor cosecha de la temporada.", "boundaries": [{"text": "Mientras ", "start": 37.609, "end": 38.05}, {"text": "vuelvo ", "start": 38.097, "end": 38.364}, {"text": "para ", "start": 38.41, "end": 38.584}, {"text": "casa, ", "start": 38.631, "end": 39.13}, {"text": "mi ", "start": 39.339, "end": 39.455}, {"text": "cesta ", "start": 39.49, "end": 39.792}, {"text": "pesa ", "start": 39.85, "end": 40.175}, {"text": "por ", "start": 40.233, "end": 40.384}, {"text": "la ", "start": 40.43, "end": 40.5}, {"text": "mejor ", "start": 40.558, "end": 40.848}, {"text": "cosecha ", "start": 40.918, "end": 41.429}, {"text": "de ", "start": 41.487, "end": 41.545}, {"text": "la ", "start": 41.591, "end": 41.661}, {"text": "temporada.", "start": 41.696, "end": 42.404}]}, {"id": "p3s2", "text": "Cocinar una comida con ingredientes tan frescos es lo mejor de mi fin de semana.", "boundaries": [{"text": "Cocinar ", "start": 42.996, "end": 43.495}, {"text": "una ", "start": 43.553, "end": 43.704}, {"text": "comida ", "start": 43.751, "end": 44.111}, {"text": "con ", "start": 44.169, "end": 44.296}, {"text": "ingredientes ", "start": 44.354, "end": 44.993}, {"text": "tan ", "start": 45.051, "end": 45.214}, {"text": "frescos ", "start": 45.283, "end": 45.829}, {"text": "es ", "start": 46.073, "end": 46.235}, {"text": "lo ", "start": 46.305, "end": 46.375}, {"text": "mejor ", "start": 46.421, "end": 46.769}, {"text": "de ", "start": 46.839, "end": 46.897}, {"text": "mi ", "start": 46.943, "end": 47.025}, {"text": "fin ", "start": 47.071, "end": 47.245}, {"text": "de ", "start": 47.292, "end": 47.361}, {"text": "semana.", "start": 47.408, "end": 47.93}]}, {"id": "p3s3", "text": "No hay nada como el sabor de la comida cultivada con tanto amor y esmero.", "boundaries": [{"text": "No ", "start": 48.522, "end": 48.673}, {"text": "hay ", "start": 48.697, "end": 48.824}, {"text": "nada ", "start": 48.894, "end": 49.207}, {"text": "como ", "start": 49.289, "end": 49.509}, {"text": "el ", "start": 49.544, "end": 49.602}, {"text": "sabor ", "start": 49.672, "end": 50.008}, {"text": "de ", "start": 50.078, "end": 50.136}, {"text": "la ", "start": 50.183, "end": 50.252}, {"text": "comida ", "start": 50.299, "end": 50.647}, {"text": "cultivada ", "start": 50.693, "end": 51.309}, {"text": "con ", "start": 51.39, "end": 51.564}, {"text": "tanto ", "start": 51.645, "end": 52.017}, {"text": "amor ", "start": 52.075, "end": 52.377}, {"text": "y ", "start": 52.47, "end": 52.539}, {"text": "esmero.", "start": 52.597, "end": 53.399}]}]}]}